binpacking/__init__.py
binpacking/binpacking_binary.py
binpacking/numpy.py
binpacking/py.typed
binpacking/to_constant_bin_number.py
binpacking/to_constant_volume.py
binpacking/utilities.py
binpacking/tests/__init__.py
binpacking/tests/conftest.py
binpacking/tests/test_cli.py
binpacking/tests/test_constant_bin_number.py
binpacking/tests/test_constant_volume.py
binpacking/tests/test_csv_operations.py
binpacking/tests/test_numpy.py
binpacking/tests/test_utilities.py
binpacking-2.0.0.dist-info/licenses/LICENSE.in
binpacking-2.0.0.dist-info/METADATA
binpacking-2.0.0.dist-info/WHEEL
binpacking-2.0.0.dist-info/entry_points.txt
binpacking-2.0.0.dist-info/top_level.txt
binpacking-2.0.0.dist-info/RECORD
