Metadata-Version: 2.4
Name: binpacking
Version: 2.0.0
Summary: Heuristic distribution of weighted items to bins (either a fixed number of bins or a fixed number of volume per bin). Data may be in form of list, dictionary, list of tuples or csv-file.
Author-email: "Benjamin F. Maier" <bfmaier@physik.hu-berlin.de>
License: MIT
Project-URL: Homepage, https://www.github.com/benmaier/binpacking
Project-URL: Repository, https://www.github.com/benmaier/binpacking
Classifier: License :: OSI Approved :: MIT License
Classifier: Programming Language :: Python :: 3
Classifier: Programming Language :: Python :: 3.10
Classifier: Programming Language :: Python :: 3.11
Classifier: Programming Language :: Python :: 3.12
Classifier: Programming Language :: Python :: 3.13
Requires-Python: >=3.10
License-File: LICENSE.in
Provides-Extra: numpy
Requires-Dist: numpy>=1.20; extra == "numpy"
Provides-Extra: dev
Requires-Dist: pytest>=7.0; extra == "dev"
Requires-Dist: pytest-cov>=4.0; extra == "dev"
Dynamic: license-file
